sphinx_iowmd_theme/.DS_Store
sphinx_iowmd_theme/__init__.py
sphinx_iowmd_theme/__init__.pyc
sphinx_iowmd_theme/drawer.html
sphinx_iowmd_theme/footer.html
sphinx_iowmd_theme/globaltoc.html
sphinx_iowmd_theme/header.html
sphinx_iowmd_theme/header_search.html
sphinx_iowmd_theme/header_sourcelink.html
sphinx_iowmd_theme/layout.html
sphinx_iowmd_theme/localtoc.html
sphinx_iowmd_theme/relations.html
sphinx_iowmd_theme/search.html
sphinx_iowmd_theme/theme.conf
sphinx_iowmd_theme/__pycache__/__init__.cpython-35.pyc
sphinx_iowmd_theme/__pycache__/__init__.cpython-36.pyc
sphinx_iowmd_theme/__pycache__/__init__.cpython-38.pyc
sphinx_iowmd_theme/static/.DS_Store
sphinx_iowmd_theme/static/material-icons.css
sphinx_iowmd_theme/static/notosanscjkjp.css
sphinx_iowmd_theme/static/roboto.css
sphinx_iowmd_theme/static/sphinx_materialdesign_theme.css
sphinx_iowmd_theme/static/sphinx_materialdesign_theme.css.map
sphinx_iowmd_theme/static/sphinx_materialdesign_theme.js
sphinx_iowmd_theme/static/font/.DS_Store
sphinx_iowmd_theme/static/font/NotoSansCJKjp/LICENSE_OFL.txt
sphinx_iowmd_theme/static/font/NotoSansCJKjp/NotoSansCJKjp-Black.ttf
sphinx_iowmd_theme/static/font/NotoSansCJKjp/NotoSansCJKjp-Black.woff
sphinx_iowmd_theme/static/font/NotoSansCJKjp/NotoSansCJKjp-Black.woff2
sphinx_iowmd_theme/static/font/NotoSansCJKjp/NotoSansCJKjp-Bold.ttf
sphinx_iowmd_theme/static/font/NotoSansCJKjp/NotoSansCJKjp-Bold.woff
sphinx_iowmd_theme/static/font/NotoSansCJKjp/NotoSansCJKjp-Bold.woff2
sphinx_iowmd_theme/static/font/NotoSansCJKjp/NotoSansCJKjp-DemiLight.ttf
sphinx_iowmd_theme/static/font/NotoSansCJKjp/NotoSansCJKjp-DemiLight.woff
sphinx_iowmd_theme/static/font/NotoSansCJKjp/NotoSansCJKjp-DemiLight.woff2
sphinx_iowmd_theme/static/font/NotoSansCJKjp/NotoSansCJKjp-Light.ttf
sphinx_iowmd_theme/static/font/NotoSansCJKjp/NotoSansCJKjp-Light.woff
sphinx_iowmd_theme/static/font/NotoSansCJKjp/NotoSansCJKjp-Light.woff2
sphinx_iowmd_theme/static/font/NotoSansCJKjp/NotoSansCJKjp-Medium.ttf
sphinx_iowmd_theme-0.0.19.dist-info/LICENSE
sphinx_iowmd_theme-0.0.19.dist-info/METADATA
sphinx_iowmd_theme-0.0.19.dist-info/WHEEL
sphinx_iowmd_theme-0.0.19.dist-info/entry_points.txt
sphinx_iowmd_theme-0.0.19.dist-info/top_level.txt
sphinx_iowmd_theme-0.0.19.dist-info/RECORD
