Metadata-Version: 2.1
Name: sphinx-iowmd-theme
Version: 0.0.19
Summary: Sphinx Material Design Theme
Home-page: https://github.com/zaniphrom/sphinx_iowmd_theme
Author: Brian Butler
Author-email: bbutler@iponweb.net
License: MIT License
Platform: UNKNOWN
Classifier: Development Status :: 5 - Production/Stable
Classifier: Environment :: Web Environment
Classifier: Intended Audience :: Developers
Classifier: Intended Audience :: System Administrators
Classifier: License :: OSI Approved :: MIT License
Classifier: Operating System :: OS Independent
Classifier: Programming Language :: Python
Classifier: Topic :: Internet
Classifier: Topic :: Software Development :: Documentation
